hailhydro/__init__.py
hailhydro/flow_init.py
hailhydro/flow_random.py
hailhydro/flux_init.py
hailhydro/flux_overflow.py
hailhydro/flux_random_overflow.py
hailhydro-0.0.1.dist-info/LICENSE
hailhydro-0.0.1.dist-info/METADATA
hailhydro-0.0.1.dist-info/WHEEL
hailhydro-0.0.1.dist-info/top_level.txt
hailhydro-0.0.1.dist-info/RECORD
