Metadata-Version: 2.1
Name: hailhydro
Version: 0.0.1
Summary: Collecton of tools for computation of flows and and fluxes on Kirchhoff circuits. 
Home-page: https://github.com/felixk1990/kirchhoff-circuit
Author: felixk1990
Author-email: felixuwekramer@protonmail.com
License: UNKNOWN
Platform: UNKNOWN
Classifier: Programming Language :: Python :: 3
Classifier: License :: OSI Approved :: MIT License
Classifier: Operating System :: OS Independent
Requires-Python: >=3.6
